htmldammit/__init__.py
htmldammit/contenttypes.py
htmldammit/core.py
htmldammit/integrations/__init__.py
htmldammit/integrations/requests.py
htmldammit/integrations/urllib.py
htmldammit-0.1.1.dist-info/DESCRIPTION.rst
htmldammit-0.1.1.dist-info/METADATA
htmldammit-0.1.1.dist-info/RECORD
htmldammit-0.1.1.dist-info/WHEEL
htmldammit-0.1.1.dist-info/metadata.json
htmldammit-0.1.1.dist-info/top_level.txt
