Metadata-Version: 2.0
Name: htmldammit
Version: 0.1.1
Summary: Make every effort to properly decode HTML, because HTML is unicode, dammit!
Home-page: https://github.com/taleinat/htmldammit
Author: Tal Einat
Author-email: taleinat@gmail.com
License: MIT
Keywords: htmldammit HTML unicode
Platform: UNKNOWN
Classifier: Development Status :: 3 - Alpha
Classifier: Intended Audience :: Developers
Classifier: License :: OSI Approved :: MIT License
Classifier: Natural Language :: English
Classifier: Programming Language :: Python :: 2
Classifier: Programming Language :: Python :: 2.7
Classifier: Programming Language :: Python :: 3
Classifier: Programming Language :: Python :: 3.3
Classifier: Programming Language :: Python :: 3.4
Classifier: Programming Language :: Python :: 3.5
Classifier: Programming Language :: Python :: 3.6
Classifier: Programming Language :: Python :: Implementation :: CPython
Classifier: Topic :: Software Development :: Libraries :: Python Modules
Requires-Dist: six
Requires-Dist: beautifulsoup4
